SimpleDeployer-1.1.0.dist-info/METADATA
SimpleDeployer-1.1.0.dist-info/RECORD
SimpleDeployer-1.1.0.dist-info/WHEEL
SimpleDeployer-1.1.0.dist-info/entry_points.txt
SimpleDeployer-1.1.0.dist-info/top_level.txt
deployer/__init__.py
deployer/deployer.py
