Metadata-Version: 2.1
Name: SimpleDeployer
Version: 1.1.0
Summary: Dead simple deployment system
Home-page: https://github.com/mikedombo/simpledeployer
Author: Michael Dombrowski
Author-email: michael@mikedombrowski.com
License: BSD-3-Clause
Platform: UNKNOWN
Requires-Dist: gitpython (>=2.1.11)
Requires-Dist: pyyaml (>=5.1)
Requires-Dist: click (>=7.0)
